adjsim/__init__.py
adjsim/analysis.py
adjsim/callback.py
adjsim/color.py
adjsim/core.py
adjsim/decision.py
adjsim/index.py
adjsim/utility.py
adjsim/visual.py
adjsim-2.1.0.dist-info/DESCRIPTION.rst
adjsim-2.1.0.dist-info/METADATA
adjsim-2.1.0.dist-info/RECORD
adjsim-2.1.0.dist-info/WHEEL
adjsim-2.1.0.dist-info/metadata.json
adjsim-2.1.0.dist-info/top_level.txt
