Metadata-Version: 2.0
Name: adjsim
Version: 2.1.0
Summary: An Agent Based Modelling Engine tailored for Reinforcement Learning.
Home-page: https://github.com/SeverTopan/AdjSim
Author: Sever Topan
Author-email: UNKNOWN
License: GPL-3.0
Keywords: agent based modelling ABM reinforcement learning
Platform: UNKNOWN
Classifier: Development Status :: 3 - Alpha
Classifier: Intended Audience :: Developers
Classifier: License :: OSI Approved :: GNU General Public License v3 (GPLv3)
Classifier: Programming Language :: Python :: 3.5
Classifier: Programming Language :: Python :: 3.6
Requires-Python: >=3.5, <3.7
Requires-Dist: PyQt5 (==5.9)
Requires-Dist: matplotlib (==2.0)
Requires-Dist: numpy (==1.13)
